crondst/__init__.py
crondst/py.typed
crondst-1.0.3.dist-info/LICENSE
crondst-1.0.3.dist-info/METADATA
crondst-1.0.3.dist-info/WHEEL
crondst-1.0.3.dist-info/top_level.txt
crondst-1.0.3.dist-info/RECORD
