Metadata-Version: 2.1
Name: crondst
Version: 1.0.3
Summary: Returns when the next job triggers given a cron expression. Supports DST.
Author: Calvin Law
Maintainer: Calvin Law
License: MIT
Project-URL: Homepage, https://github.com/lawcal/crondst
Keywords: cron,crontab,schedule
Classifier: Development Status :: 5 - Production/Stable
Classifier: Intended Audience :: Developers
Classifier: Topic :: Software Development :: Libraries :: Python Modules
Classifier: License :: OSI Approved :: MIT License
Classifier: Programming Language :: Python :: 3
Requires-Python: >=3.9
License-File: LICENSE
